[
  "ActionDsl",
  1,
  [
    "None"
  ],
  false,
  false,
  false,
  false,
  false,
  false,
  false,
  0,
  [
    "Block",
    [
      [
        "Command",
        [
          "HideCharacter",
          -17,
          210
        ]
      ],
      [
        "Command",
        [
          "ShowEffect",
          "キャラの位置の演出",
          [
            "SpecifyEffectDirectly",
            "battle/effect/skill_unique/bigwing_shaman/bigwing_shaman_player_back"
          ],
          -17,
          [
            "ForesideOfCharacter"
          ],
          [
            "SpecifyEffectLifetimeDirectly",
            210
          ],
          [
            "AB"
          ],
          0,
          0,
          0,
          true,
          false,
          [
            "None"
          ]
        ]
      ],
      [
        "Command",
        [
          "CreateHitArea",
          "*",
          -18,
          [
            "AB"
          ],
          0,
          -150,
          0,
          false,
          false,
          [
            "Circle",
            [
              {
                "max": 175,
                "min": 175
              }
            ]
          ],
          [
            "Center"
          ],
          [
            "Bottom"
          ],
          [
            "Single"
          ],
          [
            "SpecifyHitAreaLifetimeDirectly",
            185
          ],
          [
            "CalculatedUsingMaxNumOfHits",
            24
          ],
          [
            "None"
          ],
          false,
          true,
          [
            "None"
          ],
          0,
          [
            "Block",
            [
              [
                "Command",
                [
                  "ShowEffect",
                  "飛翔演出",
                  [
                    "SpecifyEffectDirectly",
                    "battle/effect/skill_unique/bigwing_shaman/bigwing_shaman_character"
                  ],
                  0,
                  [
                    "ForesideOfCharacter"
                  ],
                  [
                    "SpecifyEffectLifetimeDirectly",
                    185
                  ],
                  [
                    "AB"
                  ],
                  0,
                  0,
                  0,
                  false,
                  false,
                  [
                    "None"
                  ]
                ]
              ],
              [
                "Command",
                [
                  "ShowEffect",
                  "竜巻演出",
                  [
                    "SpecifyEffectDirectly",
                    "battle/effect/skill_unique/bigwing_shaman/bigwing_shaman_tornado"
                  ],
                  0,
                  [
                    "ForesideOfCharacter"
                  ],
                  [
                    "SpecifyEffectLifetimeDirectly",
                    185
                  ],
                  [
                    "AB"
                  ],
                  0,
                  -180,
                  0,
                  false,
                  false,
                  [
                    "Some",
                    [
                      {
                        "max": 3.5,
                        "min": 3.5
                      }
                    ]
                  ]
                ]
              ]
            ]
          ],
          1,
          2,
          [
            "Block",
            [
              [
                "Command",
                [
                  "CreateNormalAttack",
                  2,
                  255,
                  null,
                  null,
                  5,
                  [
                    {
                      "max": 0.75,
                      "min": 0.6458333333333334
                    }
                  ],
                  [
                    {
                      "max": 0,
                      "min": 0
                    }
                  ],
                  true,
                  false,
                  false,
                  false,
                  false,
                  [
                    {
                      "max": 0.5,
                      "min": 0.5
                    }
                  ],
                  [
                    {
                      "max": 0.5833333333333334,
                      "min": 0.5833333333333334
                    }
                  ],
                  [
                    "Fine"
                  ],
                  true
                ]
              ],
              [
                "Command",
                [
                  "ShakeCamera",
                  1
                ]
              ]
            ]
          ],
          0,
          0,
          [
            "None"
          ]
        ]
      ],
      [
        "Command",
        [
          "FindAllSubjects",
          3,
          33,
          null,
          null,
          null,
          null,
          null,
          [
            "DoNothing"
          ],
          [
            "Block",
            [
              [
                "Command",
                [
                  "CreateCondition",
                  3,
                  [
                    [
                      "ACFlying",
                      [
                        {
                          "max": 720,
                          "min": 600
                        }
                      ]
                    ]
                  ],
                  [
                    {
                      "max": 1,
                      "min": 1
                    }
                  ],
                  [
                    "None"
                  ],
                  true,
                  false,
                  "",
                  null,
                  false,
                  3,
                  [
                    {
                      "max": 1,
                      "min": 1
                    }
                  ],
                  false
                ]
              ]
            ]
          ]
        ]
      ]
    ]
  ]
]
