[
  "ActionDsl",
  2,
  [
    "None"
  ],
  false,
  false,
  false,
  false,
  false,
  false,
  false,
  0,
  [
    "Block",
    [
      [
        "Command",
        [
          "StopBall",
          -18,
          75,
          [
            "Stop"
          ],
          [
            "AB"
          ],
          0
        ]
      ],
      [
        "Command",
        [
          "ShowEffect",
          "扇子を開く",
          [
            "SpecifyEffectDirectly",
            "battle/effect/skill_unique/outlaw_panther_ny22/outlaw_panther_ny22_open"
          ],
          -18,
          [
            "ForesideOfCharacter"
          ],
          [
            "PlayOnlyFirstSequence"
          ],
          [
            "AB"
          ],
          0,
          0,
          0,
          true,
          false,
          [
            "None"
          ]
        ]
      ],
      [
        "Event",
        [
          "Wait",
          10,
          "*",
          [
            "Block",
            [
              [
                "Command",
                [
                  "CreateHitArea",
                  "*",
                  -18,
                  [
                    "AB"
                  ],
                  0,
                  0,
                  0,
                  true,
                  false,
                  [
                    "Circle",
                    [
                      {
                        "max": 300,
                        "min": 300
                      }
                    ]
                  ],
                  [
                    "Center"
                  ],
                  [
                    "Center"
                  ],
                  [
                    "Single"
                  ],
                  [
                    "SpecifyHitAreaLifetimeDirectly",
                    60
                  ],
                  [
                    "CalculatedUsingMaxNumOfHits",
                    15
                  ],
                  [
                    "Some",
                    [
                      {
                        "max": 15,
                        "min": 15
                      }
                    ]
                  ],
                  false,
                  true,
                  [
                    "None"
                  ],
                  0,
                  [
                    "Block",
                    [
                      [
                        "Command",
                        [
                          "ShowEffect",
                          "回転演出",
                          [
                            "SpecifyEffectDirectly",
                            "battle/effect/skill_unique/outlaw_panther_ny22/outlaw_panther_ny22_rotation"
                          ],
                          -18,
                          [
                            "ForesideOfCharacter"
                          ],
                          [
                            "SpecifyEffectLifetimeDirectly",
                            60
                          ],
                          [
                            "AB"
                          ],
                          0,
                          0,
                          0,
                          true,
                          false,
                          [
                            "Some",
                            [
                              {
                                "max": 6,
                                "min": 6
                              }
                            ]
                          ]
                        ]
                      ],
                      [
                        "Command",
                        [
                          "ShowEffect",
                          "紙吹雪演出",
                          [
                            "SpecifyEffectDirectly",
                            "battle/effect/skill_unique/outlaw_panther_ny22/outlaw_panther_ny22_kamihubuki"
                          ],
                          -18,
                          [
                            "ForesideOfCharacter"
                          ],
                          [
                            "SpecifyEffectLifetimeDirectly",
                            60
                          ],
                          [
                            "AB"
                          ],
                          0,
                          0,
                          0,
                          true,
                          false,
                          [
                            "None"
                          ]
                        ]
                      ]
                    ]
                  ],
                  1,
                  2,
                  [
                    "Block",
                    [
                      [
                        "Command",
                        [
                          "ShakeCamera",
                          1
                        ]
                      ],
                      [
                        "Command",
                        [
                          "CreateNormalAttack",
                          2,
                          255,
                          null,
                          null,
                          5,
                          [
                            {
                              "max": 0.5333333333333333,
                              "min": 0.5333333333333333
                            }
                          ],
                          [
                            {
                              "max": 0,
                              "min": 0
                            }
                          ],
                          false,
                          false,
                          false,
                          false,
                          false,
                          [
                            {
                              "max": 0.8,
                              "min": 0.8
                            }
                          ],
                          [
                            {
                              "max": 0.8,
                              "min": 0.8
                            }
                          ],
                          [
                            "Fine"
                          ],
                          true
                        ]
                      ]
                    ]
                  ],
                  0,
                  0,
                  [
                    "None"
                  ]
                ]
              ],
              [
                "Event",
                [
                  "Wait",
                  59,
                  "*",
                  [
                    "Block",
                    [
                      [
                        "Command",
                        [
                          "ShowEffect",
                          "終了演出",
                          [
                            "SpecifyEffectDirectly",
                            "battle/effect/skill_unique/outlaw_panther_ny22/outlaw_panther_ny22_close"
                          ],
                          -18,
                          [
                            "ForesideOfCharacter"
                          ],
                          [
                            "PlayOnlyFirstSequence"
                          ],
                          [
                            "AB"
                          ],
                          0,
                          0,
                          0,
                          true,
                          false,
                          [
                            "None"
                          ]
                        ]
                      ]
                    ]
                  ]
                ]
              ]
            ]
          ]
        ]
      ],
      [
        "Command",
        [
          "FindAllSubjects",
          3,
          33,
          null,
          null,
          null,
          null,
          null,
          [
            "DoNothing"
          ],
          [
            "Block",
            [
              [
                "Command",
                [
                  "CreateCondition",
                  3,
                  [
                    [
                      "ACPowerFlipDamage",
                      [
                        {
                          "max": 720,
                          "min": 720
                        }
                      ],
                      [
                        {
                          "max": 0.3,
                          "min": 0.3
                        }
                      ],
                      [
                        {
                          "max": 1,
                          "min": 1
                        }
                      ]
                    ]
                  ],
                  [
                    {
                      "max": 1,
                      "min": 1
                    }
                  ],
                  [
                    "GenericConditionHitEffect"
                  ],
                  true,
                  false,
                  "",
                  null,
                  false,
                  3,
                  [
                    {
                      "max": 1,
                      "min": 1
                    }
                  ],
                  false
                ]
              ]
            ]
          ]
        ]
      ]
    ]
  ]
]
