[
  "ActionDsl",
  3,
  [
    "None"
  ],
  false,
  false,
  false,
  false,
  false,
  false,
  false,
  0,
  [
    "Block",
    [
      [
        "Command",
        [
          "StopBall",
          -18,
          19,
          [
            "Stop"
          ],
          [
            "AB"
          ],
          0
        ]
      ],
      [
        "Command",
        [
          "ShowEffect",
          "チャージ演出",
          [
            "ResolveByElement",
            "battle/effect/skill_general/decoration/heavy_charge",
            255
          ],
          -18,
          [
            "ForesideOfCharacter"
          ],
          [
            "SpecifyEffectLifetimeDirectly",
            20
          ],
          [
            "AB"
          ],
          0,
          0,
          0,
          true,
          false,
          [
            "Some",
            [
              {
                "max": 1,
                "min": 1
              }
            ]
          ]
        ]
      ],
      [
        "Event",
        [
          "Wait",
          20,
          "*",
          [
            "Block",
            [
              [
                "Command",
                [
                  "MoveBall",
                  -18,
                  [
                    "AB"
                  ],
                  0,
                  15,
                  20,
                  [
                    "Stop"
                  ],
                  false
                ]
              ],
              [
                "Event",
                [
                  "Wait",
                  14,
                  "*",
                  [
                    "Block",
                    [
                      [
                        "Command",
                        [
                          "StopBall",
                          -18,
                          1,
                          [
                            "Stop"
                          ],
                          [
                            "AB"
                          ],
                          0
                        ]
                      ]
                    ]
                  ]
                ]
              ],
              [
                "Command",
                [
                  "ShowEffect",
                  "オーラ演出",
                  [
                    "ResolveByElement",
                    "battle/effect/skill_general/decoration/rush_aura",
                    255
                  ],
                  -18,
                  [
                    "ForesideOfCharacter"
                  ],
                  [
                    "SpecifyEffectLifetimeDirectly",
                    30
                  ],
                  [
                    "EF"
                  ],
                  0,
                  0,
                  3.141592653589793,
                  true,
                  false,
                  [
                    "Some",
                    [
                      {
                        "max": 1,
                        "min": 1
                      }
                    ]
                  ]
                ]
              ],
              [
                "Event",
                [
                  "Wait",
                  15,
                  "*",
                  [
                    "Block",
                    [
                      [
                        "Command",
                        [
                          "CreateReferencePoint",
                          -18,
                          [
                            "AB"
                          ],
                          0,
                          0,
                          0,
                          false,
                          false,
                          [
                            "Single"
                          ],
                          50,
                          0,
                          [
                            "Block",
                            [
                              [
                                "Command",
                                [
                                  "CreateHitArea",
                                  "*",
                                  0,
                                  [
                                    "AB"
                                  ],
                                  0,
                                  0,
                                  0,
                                  true,
                                  false,
                                  [
                                    "Rectangle",
                                    [
                                      {
                                        "max": 300,
                                        "min": 300
                                      }
                                    ],
                                    [
                                      {
                                        "max": 150,
                                        "min": 150
                                      }
                                    ]
                                  ],
                                  [
                                    "Center"
                                  ],
                                  [
                                    "Bottom"
                                  ],
                                  [
                                    "Single"
                                  ],
                                  [
                                    "SpecifyHitAreaLifetimeDirectly",
                                    20
                                  ],
                                  [
                                    "CalculatedUsingMaxNumOfHits",
                                    1
                                  ],
                                  [
                                    "None"
                                  ],
                                  false,
                                  true,
                                  [
                                    "None"
                                  ],
                                  1,
                                  [
                                    "Block",
                                    [
                                      [
                                        "Command",
                                        [
                                          "ShakeCamera",
                                          2
                                        ]
                                      ],
                                      [
                                        "Command",
                                        [
                                          "ShowEffect",
                                          "攻撃演出",
                                          [
                                            "ResolveByElement",
                                            "battle/effect/skill_general/area/cutting_front",
                                            255
                                          ],
                                          0,
                                          [
                                            "ForesideOfCharacter"
                                          ],
                                          [
                                            "PlayOnlyFirstSequence"
                                          ],
                                          [
                                            "AB"
                                          ],
                                          0,
                                          0,
                                          0,
                                          true,
                                          false,
                                          [
                                            "Some",
                                            [
                                              {
                                                "max": 3,
                                                "min": 3
                                              }
                                            ]
                                          ]
                                        ]
                                      ]
                                    ]
                                  ],
                                  2,
                                  3,
                                  [
                                    "Block",
                                    [
                                      [
                                        "Command",
                                        [
                                          "CreateNormalAttack",
                                          3,
                                          255,
                                          null,
                                          null,
                                          100,
                                          [
                                            {
                                              "max": 15,
                                              "min": 13
                                            }
                                          ],
                                          [
                                            {
                                              "max": 0,
                                              "min": 0
                                            }
                                          ],
                                          false,
                                          false,
                                          false,
                                          false,
                                          false,
                                          [
                                            {
                                              "max": 15,
                                              "min": 15
                                            }
                                          ],
                                          [
                                            {
                                              "max": 15,
                                              "min": 15
                                            }
                                          ],
                                          [
                                            "Coarse"
                                          ],
                                          true
                                        ]
                                      ]
                                    ]
                                  ],
                                  0,
                                  0,
                                  [
                                    "None"
                                  ]
                                ]
                              ]
                            ]
                          ]
                        ]
                      ]
                    ]
                  ]
                ]
              ]
            ]
          ]
        ]
      ],
      [
        "Command",
        [
          "CreateCondition",
          -17,
          [
            [
              "ACAttackPoint",
              [
                {
                  "max": 900,
                  "min": 900
                }
              ],
              [
                {
                  "max": 0.75,
                  "min": 0.65
                }
              ],
              [
                {
                  "max": 1,
                  "min": 1
                }
              ]
            ]
          ],
          [
            {
              "max": 1,
              "min": 1
            }
          ],
          [
            "GenericConditionHitEffect"
          ],
          true,
          false,
          "",
          null,
          false,
          3,
          [
            {
              "max": 1,
              "min": 1
            }
          ],
          false
        ]
      ]
    ]
  ]
]
