{
  "obtainable_mana_1": [
    [
      "1",
      "",
      "obtainable_mana_1",
      ""
    ]
  ],
  "condition_flying": [
    [
      "0",
      "condition_flying",
      "",
      "1800"
    ]
  ],
  "condition_invincible": [
    [
      "0",
      "condition_invincible",
      "",
      "1800"
    ]
  ],
  "condition_piercing": [
    [
      "0",
      "condition_piercing",
      "",
      "1800"
    ]
  ],
  "condition_cure_all": [
    [
      "0",
      "condition_cure_all",
      "",
      "1800"
    ]
  ],
  "hp_recovery_small": [
    [
      "0",
      "hp_recovery_small",
      "",
      "216000"
    ]
  ],
  "hp_recovery_middle": [
    [
      "0",
      "hp_recovery_middle",
      "",
      "216000"
    ]
  ],
  "hp_recovery_large": [
    [
      "0",
      "hp_recovery_large",
      "",
      "216000"
    ]
  ],
  "attack_power_up": [
    [
      "0",
      "attack_power_up",
      "",
      "216000"
    ]
  ],
  "damage_cut": [
    [
      "0",
      "damage_cut",
      "",
      "216000"
    ]
  ],
  "skill_charge_small": [
    [
      "0",
      "skill_charge_small",
      "",
      "216000"
    ]
  ],
  "skill_charge_middle": [
    [
      "0",
      "skill_charge_middle",
      "",
      "216000"
    ]
  ],
  "skill_charge_large": [
    [
      "0",
      "skill_charge_large",
      "",
      "216000"
    ]
  ],
  "skill_charge_large_wait_short": [
    [
      "0",
      "skill_charge_large",
      "",
      "300"
    ]
  ],
  "skill_charge_large_once": [
    [
      "0",
      "skill_charge_large",
      "",
      "99999999"
    ]
  ],
  "condition_flying_once": [
    [
      "0",
      "condition_flying",
      "",
      "99999999"
    ]
  ],
  "condition_piercing_once": [
    [
      "0",
      "condition_piercing",
      "",
      "99999999"
    ]
  ],
  "attack_power_up_once": [
    [
      "0",
      "attack_power_up",
      "",
      "99999999"
    ]
  ],
  "condition_speedup": [
    [
      "0",
      "condition_speedup",
      "",
      "1800"
    ]
  ],
  "accumulation_attack_power_up_low": [
    [
      "0",
      "accumulation_attack_power_up_low",
      "",
      "99999999"
    ]
  ],
  "accumulation_attack_power_up_summer22_helicopter": [
    [
      "0",
      "accumulation_attack_power_up_summer22_helicopter",
      "",
      "216000"
    ]
  ],
  "attack_power_up_accumulation": [
    [
      "0",
      "attack_power_up_accumulation",
      "",
      "3600"
    ]
  ],
  "attack_power_up_accumulation_spirit_beast_light": [
    [
      "0",
      "attack_power_up_accumulation_spirit_beast_light",
      "",
      "3600"
    ]
  ],
  "additional_direct_attack_spirit_beast_light": [
    [
      "0",
      "additional_direct_attack_spirit_beast_light",
      "",
      "3600"
    ]
  ],
  "speedup_spirit_beast_light": [
    [
      "0",
      "speedup_spirit_beast_light",
      "",
      "3600"
    ]
  ],
  "condition_speedup_20_15": [
    [
      "0",
      "condition_speedup_20_15",
      "",
      "3600"
    ]
  ],
  "skill_power_up": [
    [
      "0",
      "skill_power_up",
      "",
      "3600"
    ]
  ],
  "accumulation_attack_power_up_shark": [
    [
      "0",
      "accumulation_attack_power_up_shark",
      "",
      "216000"
    ]
  ],
  "accumulation_attack_power_up_reine_rouge": [
    [
      "0",
      "attack_power_up_accumulation",
      "",
      "2700"
    ]
  ],
  "accumulation_attack_power_up_raid": [
    [
      "0",
      "accumulation_attack_power_up_raid",
      "",
      "1800"
    ]
  ],
  "hp_recovery_middle_once": [
    [
      "0",
      "hp_recovery_middle",
      "",
      "99999999"
    ]
  ],
  "attack_power_up_25_250": [
    [
      "0",
      "attack_power_up_25_250",
      "",
      "216000"
    ]
  ],
  "attack_power_up_orochi_ex": [
    [
      "0",
      "attack_power_up_orochi_ex",
      "",
      "3600"
    ]
  ],
  "attack_power_up_hungry_dragon": [
    [
      "0",
      "attack_power_up_hungry_dragon",
      "",
      "3600"
    ]
  ],
  "accumulation_attack_power_up": [
    [
      "0",
      "accumulation_attack_power_up",
      "",
      "216000"
    ]
  ],
  "accumulation_attack_power_up_haniwa_dark": [
    [
      "0",
      "accumulation_attack_power_up_haniwa_dark",
      "",
      "216000"
    ]
  ],
  "accumulation_attack_power_up_haniwa_thunder": [
    [
      "0",
      "accumulation_attack_power_up_haniwa_thunder",
      "",
      "216000"
    ]
  ],
  "attack_power_up_grizzly": [
    [
      "0",
      "attack_power_up_grizzly",
      "",
      "3600"
    ]
  ],
  "condition_piercing_grizzly": [
    [
      "0",
      "condition_piercing",
      "",
      "3600"
    ]
  ],
  "attack_power_up_ghost_fox_ex": [
    [
      "0",
      "attack_power_up_ghost_fox_ex",
      "",
      "1800"
    ]
  ],
  "accumulation_attack_power_up2": [
    [
      "0",
      "accumulation_attack_power_up2",
      "",
      "3600"
    ]
  ],
  "condition_additional_direct_attack": [
    [
      "0",
      "condition_additional_direct_attack",
      "",
      "3600"
    ]
  ],
  "accumulation_direct_attack_power_up_u_collabo": [
    [
      "0",
      "accumulation_direct_attack_power_up_u_collabo",
      "",
      "3600"
    ]
  ],
  "accumulation_attack_power_up_25_500": [
    [
      "0",
      "accumulation_attack_power_up_25_500",
      "",
      "9999"
    ]
  ]
}
